ptask/__init__.py
ptask/__main__.py
ptask/const.py
ptask/process.py
ptask/tasks.py
ptask/utils.py
ptask-0.0.1.dist-info/LICENSE
ptask-0.0.1.dist-info/METADATA
ptask-0.0.1.dist-info/WHEEL
ptask-0.0.1.dist-info/entry_points.txt
ptask-0.0.1.dist-info/top_level.txt
ptask-0.0.1.dist-info/RECORD
