Metadata-Version: 2.1
Name: ptask
Version: 0.0.1
Summary: attr: ptask.__doc__
Home-page: https://codeberg.org/pantlesscoder/painless_project
Author: Pantless Coder (Nghia Lam)
Author-email: nghialam@gmx.com
License: MIT
Classifier: Programming Language :: Python
Classifier: License :: OSI Approved :: MIT License
Classifier: Operating System :: OS Independent
Requires-Python: >=3.9
License-File: LICENSE
